{
  "score": -1,
  "sources": [
    "timesfm_lite"
  ],
  "reason": "TimesFM-Lite: p_dir=0.45 conf=LOW pred=74.18 Q10=70.54~Q90=78.02",
  "details": {
    "timesfm_lite": {
      "score": -0.6,
      "p_direction": 0.45,
      "confidence": "LOW",
      "pred_price": 74.18,
      "q10": 70.54,
      "q25": 72.24,
      "q75": 76.18,
      "q90": 78.02,
      "band_pct": 9.89,
      "r_sq": 0.507,
      "vol_h": 2.98,
      "regime_coeff": 0.8
    }
  },
  "ts": 1782881234.0641818,
  "expires": 1782884834.064182,
  "symbol": "SOLUSDT",
  "direction": "SHORT"
}